Metadata-Version: 2.1
Name: uncleprofilek
Version: 0.0.3
Summary: uncleprofilek by Kanaplakem
Home-page: https://github.com/Kanaplakem/Uncleprofilek
Author: Kanaplaken
Author-email: T_Tzzz4@hotmail.com
License: MIT
Download-URL: https://github.com/Kanaplakem/Uncleprofilek/archive/v0.0.3.zip
Keywords: Profile,Uncle,Kanaplakem
Platform: UNKNOWN
Classifier: Development Status :: 3 - Alpha
Classifier: Intended Audience :: Education
Classifier: Topic :: Utilities
Classifier: License :: OSI Approved :: MIT License
Classifier: Programming Language :: Python :: 3
Classifier: Programming Language :: Python :: 3.4
Classifier: Programming Language :: Python :: 3.5
Classifier: Programming Language :: Python :: 3.6
Classifier: Programming Language :: Python :: 3.7
Classifier: Programming Language :: Python :: 3.8
Classifier: Programming Language :: Python :: 3.9
Classifier: Programming Language :: Python :: 3.10
License-File: LICENSE.txt
